md_manager/_Files.py
md_manager/_PDB.py
md_manager/_Traj.py
md_manager/__init__.py
md_manager/df_utils.py
md_manager/parameters.py
md_manager/py.typed
md_manager/universe2df_relation.py
md_manager/CUTABI/CUTABI.py
md_manager/CUTABI/__init__.py
md_manager/NMA/_ANM.py
md_manager/NMA/__init__.py
md_manager-2.4.1.dist-info/licenses/LICENSE
md_manager-2.4.1.dist-info/METADATA
md_manager-2.4.1.dist-info/WHEEL
md_manager-2.4.1.dist-info/top_level.txt
md_manager-2.4.1.dist-info/RECORD
