Metadata-Version: 2.4
Name: md-manager
Version: 2.4.1
Summary: A python module that allow molecular dynamics data analysis based on pandas DataFrames.
Author-email: Nicolas Petiot <nicolaspetiot2710@hotmail.fr>
License:                     GNU AFFERO GENERAL PUBLIC LICENSE
Project-URL: Homepage, https://github.com/NicolasPetiot/md_manager
Project-URL: Repository, https://github.com/NicolasPetiot/md_manager
Project-URL: Issues, https://github.com/NicolasPetiot/md_manager/issues
Requires-Python: >=3.12
License-File: LICENSE
Requires-Dist: mdanalysis>=2.9.0
Requires-Dist: networkx>=3.5
Requires-Dist: numba>=0.62.1
Requires-Dist: numpy>=2.3.3
Requires-Dist: pandas>=2.3.3
Requires-Dist: scipy>=1.16.2
Requires-Dist: twine>=6.2.0
Dynamic: license-file
